AUTHORS.rst
HISTORY.rst
LICENSE
MANIFEST.in
README.rst
setup.py
django_briteverify/__init__.py
django_briteverify/api.py
django_briteverify/forms.py
django_briteverify.egg-info/PKG-INFO
django_briteverify.egg-info/SOURCES.txt
django_briteverify.egg-info/dependency_links.txt
django_briteverify.egg-info/requires.txt
django_briteverify.egg-info/top_level.txt