Metadata-Version: 1.1
Name: django-briteverify
Version: 1.0
Summary: Integration with briteverify API
Home-page: https://github.com/uploadcare/django-briteverify
Author: Uploadcare LLC
Author-email: hello@uploadcare.com
License: MIT
Keywords: django briteverify
Platform: UNKNOWN
Classifier: Development Status :: 5 - Production/Stable
Classifier: Intended Audience :: Developers
Classifier: License :: OSI Approved :: MIT License
Classifier: Natural Language :: English
Classifier: Programming Language :: Python :: 2
Classifier: Programming Language :: Python :: 2.6
Classifier: Programming Language :: Python :: 2.7
Classifier: Programming Language :: Python :: 3
Classifier: Programming Language :: Python :: 3.2
Classifier: Programming Language :: Python :: 3.3
Classifier: Programming Language :: Python :: 3.4
